yunpy/__init__.py
yunpy/character.py
yunpy/cli.py
yunpy/core.py
yunpy/utils.py
yunpy/example_input/__init__.py
yunpy/example_input/example.txt
yunpy/sources/__init__.py
yunpy/sources/phonoML_characters.csv
yunpy-0.1.1.dist-info/licenses/AUTHORS.md
yunpy-0.1.1.dist-info/licenses/LICENSE
yunpy-0.1.1.dist-info/METADATA
yunpy-0.1.1.dist-info/WHEEL
yunpy-0.1.1.dist-info/entry_points.txt
yunpy-0.1.1.dist-info/top_level.txt
yunpy-0.1.1.dist-info/RECORD
