Metadata-Version: 2.4
Name: yunpy
Version: 0.1.1
Summary: A library for phonetic annotation in Middle Chinese
Author-email: Alexander DELAPORTE <alexander.delaporte@cnrs.fr>, Qingqing XIE <qingqing.hsieh@gmail.com>
Maintainer-email: Alexander DELAPORTE <alexander.delaporte@cnrs.fr>
License-Expression: MIT
Project-URL: Repository, https://github.com/alxdrdelaporte/yunpy
Project-URL: Issues, https://github.com/alxdrdelaporte/yunpy/issues
Keywords: phonetics,phonology,Middle Chinese,chinese,linguistics,historical linguistics
Classifier: Programming Language :: Python :: 3
Classifier: Operating System :: OS Independent
Classifier: Topic :: Scientific/Engineering
Classifier: Topic :: Text Processing :: Linguistic
Classifier: Intended Audience :: Science/Research
Requires-Python: >=3.9
License-File: LICENSE
License-File: AUTHORS.md
Provides-Extra: dev
Requires-Dist: pytest>=8.4.1; extra == "dev"
Requires-Dist: black; extra == "dev"
Requires-Dist: flake8; extra == "dev"
Requires-Dist: setuptools>=80.9.0; extra == "dev"
Requires-Dist: wheel; extra == "dev"
Dynamic: license-file
